LICENSE
MANIFEST.in
README.md
setup.py
django_sshkm.egg-info/PKG-INFO
django_sshkm.egg-info/SOURCES.txt
django_sshkm.egg-info/dependency_links.txt
django_sshkm.egg-info/requires.txt
django_sshkm.egg-info/top_level.txt
sshkm/__init__.py
sshkm/celery.py
sshkm/forms.py
sshkm/models.py
sshkm/settings.py
sshkm/tasks.py
sshkm/urls.py
sshkm/wsgi.py
sshkm/fixtures/setup.json
sshkm/migrations/0001_initial.py
sshkm/migrations/0002_host_superuser.py
sshkm/migrations/0003_host_last_status.py
sshkm/migrations/__init__.py
sshkm/static/custom.css
sshkm/static/custom.js
sshkm/static/favicon.png
sshkm/static/bootstrap/LICENSE
sshkm/static/bootstrap-dialog/bootstrap-dialog.min.css
sshkm/static/bootstrap-dialog/bootstrap-dialog.min.js
sshkm/static/bootstrap/css/bootstrap-theme.css
sshkm/static/bootstrap/css/bootstrap-theme.css.map
sshkm/static/bootstrap/css/bootstrap-theme.min.css
sshkm/static/bootstrap/css/bootstrap-theme.min.css.map
sshkm/static/bootstrap/css/bootstrap.css
sshkm/static/bootstrap/css/bootstrap.css.map
sshkm/static/bootstrap/css/bootstrap.min.css
sshkm/static/bootstrap/css/bootstrap.min.css.map
sshkm/static/bootstrap/fonts/glyphicons-halflings-regular.eot
sshkm/static/bootstrap/fonts/glyphicons-halflings-regular.svg
sshkm/static/bootstrap/fonts/glyphicons-halflings-regular.ttf
sshkm/static/bootstrap/fonts/glyphicons-halflings-regular.woff
sshkm/static/bootstrap/fonts/glyphicons-halflings-regular.woff2
sshkm/static/bootstrap/js/bootstrap.js
sshkm/static/bootstrap/js/bootstrap.min.js
sshkm/static/bootstrap/js/npm.js
sshkm/static/datatables/jquery.dataTables.css
sshkm/static/datatables/jquery.dataTables.js
sshkm/static/jquery/jquery.min.js
sshkm/templates/sshkm/base.html
sshkm/templates/sshkm/docs.html
sshkm/templates/sshkm/firststeps.html
sshkm/templates/sshkm/index.html
sshkm/templates/sshkm/login.html
sshkm/templates/sshkm/group/detail.html
sshkm/templates/sshkm/group/list.html
sshkm/templates/sshkm/host/detail.html
sshkm/templates/sshkm/host/list.html
sshkm/templates/sshkm/key/detail.html
sshkm/templates/sshkm/key/list.html
sshkm/templates/sshkm/osuser/detail.html
sshkm/templates/sshkm/osuser/list.html
