Metadata-Version: 1.1
Name: django-sshkm
Version: 0.1.11
Summary: A Django based ssh-key management tool.
Home-page: https://github.com/sshkm/django-sshkm
Author: Peter Loeffler
Author-email: sshkm@guruz.at
License: GNU General Public License v3 (GPLv3)
Download-URL: https://github.com/sshkm/django-sshkm/archive/0.1.11.zip
Keywords: ssh,keymaster,sshkm,ssh-key,public key,key management
Platform: UNKNOWN
Classifier: Development Status :: 5 - Production/Stable
Classifier: Environment :: Web Environment
Classifier: Framework :: Django
Classifier: Framework :: Django :: 1.8
Classifier: Framework :: Django :: 1.9
Classifier: Framework :: Django :: 1.10
Classifier: Intended Audience :: System Administrators
Classifier: Intended Audience :: Developers
Classifier: Intended Audience :: Information Technology
Classifier: License :: OSI Approved :: GNU General Public License v3 (GPLv3)
Classifier: Natural Language :: English
Classifier: Natural Language :: German
Classifier: Operating System :: Unix
Classifier: Operating System :: POSIX :: Linux
Classifier: Programming Language :: Python
Classifier: Programming Language :: Python :: 2
Classifier: Programming Language :: Python :: 2.7
Classifier: Programming Language :: Python :: 3
Classifier: Programming Language :: Python :: 3.4
Classifier: Programming Language :: Python :: 3.5
Classifier: Programming Language :: Python :: 3.6
Classifier: Topic :: Utilities
Classifier: Topic :: System :: Systems Administration
